hatemile_for_django/__init__.py
hatemile_for_django/middleware.py
hatemile_for_django/static/hatemile_for_django/css/hide_changes.css
hatemile_for_django/static/hatemile_for_django/js/common.js
hatemile_for_django/static/hatemile_for_django/js/eventlistener.js
hatemile_for_django/static/hatemile_for_django/js/include.js
hatemile_for_django/static/hatemile_for_django/js/scriptlist_validation_fields.js
hatemile_for_django/static/hatemile_for_django/js/validation.js
hatemile_for_django-1.0.0.dist-info/METADATA
hatemile_for_django-1.0.0.dist-info/RECORD
hatemile_for_django-1.0.0.dist-info/WHEEL
hatemile_for_django-1.0.0.dist-info/top_level.txt
